odoo/addons/currency_rate_inverted/README.rst
odoo/addons/currency_rate_inverted/__init__.py
odoo/addons/currency_rate_inverted/__manifest__.py
odoo/addons/currency_rate_inverted/i18n/ca.po
odoo/addons/currency_rate_inverted/i18n/currency_rate_inverted.pot
odoo/addons/currency_rate_inverted/i18n/es.po
odoo/addons/currency_rate_inverted/i18n/es_AR.po
odoo/addons/currency_rate_inverted/i18n/fr.po
odoo/addons/currency_rate_inverted/i18n/hr.po
odoo/addons/currency_rate_inverted/models/__init__.py
odoo/addons/currency_rate_inverted/models/res_currency.py
odoo/addons/currency_rate_inverted/readme/CONFIGURE.rst
odoo/addons/currency_rate_inverted/readme/CONTRIBUTORS.rst
odoo/addons/currency_rate_inverted/readme/DESCRIPTION.rst
odoo/addons/currency_rate_inverted/static/description/icon.png
odoo/addons/currency_rate_inverted/static/description/index.html
odoo/addons/currency_rate_inverted/tests/__init__.py
odoo/addons/currency_rate_inverted/tests/test_currency_rate_inverted.py
odoo/addons/currency_rate_inverted/views/res_currency_view.xml
odoo14_addon_currency_rate_inverted-14.0.1.0.2.dist-info/METADATA
odoo14_addon_currency_rate_inverted-14.0.1.0.2.dist-info/WHEEL
odoo14_addon_currency_rate_inverted-14.0.1.0.2.dist-info/top_level.txt
odoo14_addon_currency_rate_inverted-14.0.1.0.2.dist-info/RECORD
